odoo/addons/account_analytic_tag_distribution/README.rst
odoo/addons/account_analytic_tag_distribution/__init__.py
odoo/addons/account_analytic_tag_distribution/__manifest__.py
odoo/addons/account_analytic_tag_distribution/i18n/account_analytic_tag_distribution.pot
odoo/addons/account_analytic_tag_distribution/i18n/es.po
odoo/addons/account_analytic_tag_distribution/i18n/eu_ES.po
odoo/addons/account_analytic_tag_distribution/i18n/it.po
odoo/addons/account_analytic_tag_distribution/i18n/pt_BR.po
odoo/addons/account_analytic_tag_distribution/models/__init__.py
odoo/addons/account_analytic_tag_distribution/models/account_analytic_tag.py
odoo/addons/account_analytic_tag_distribution/models/account_move_line.py
odoo/addons/account_analytic_tag_distribution/readme/CONTRIBUTORS.rst
odoo/addons/account_analytic_tag_distribution/readme/DESCRIPTION.rst
odoo/addons/account_analytic_tag_distribution/readme/USAGE.rst
odoo/addons/account_analytic_tag_distribution/static/description/icon.png
odoo/addons/account_analytic_tag_distribution/static/description/index.html
odoo/addons/account_analytic_tag_distribution/tests/__init__.py
odoo/addons/account_analytic_tag_distribution/tests/test_account_analytic_tag_distribution.py
odoo/addons/account_analytic_tag_distribution/views/account_analytic_tag_views.xml
odoo_addon_account_analytic_tag_distribution-16.0.1.0.2.6.dist-info/METADATA
odoo_addon_account_analytic_tag_distribution-16.0.1.0.2.6.dist-info/WHEEL
odoo_addon_account_analytic_tag_distribution-16.0.1.0.2.6.dist-info/top_level.txt
odoo_addon_account_analytic_tag_distribution-16.0.1.0.2.6.dist-info/RECORD
