Metadata-Version: 2.1
Name: odoo-addon-account_analytic_tag_distribution
Version: 16.0.1.0.2.6
Summary: Account Analytic Tag Distribution
Home-page: https://github.com/OCA/account-analytic
Author: Tecnativa, Odoo Community Association (OCA)
Author-email: support@odoo-community.org
License: AGPL-3
Classifier: Programming Language :: Python
Classifier: Framework :: Odoo
Classifier: Framework :: Odoo :: 16.0
Classifier: License :: OSI Approved :: GNU Affero General Public License v3
Requires-Python: >=3.10
Requires-Dist: odoo-addon-account-analytic-tag<16.1dev,>=16.0dev
Requires-Dist: odoo<16.1dev,>=16.0a
